[{"prefab_name":"Assets/Game/CardBacks/Default/Card_Back_Default","enabled":true,"description":"","source_description":"","id":0,"name":"怀旧经典","source":"startup","note_desc":"Classic"},{"prefab_name":"Assets/Game/CardBacks/S001_Pandaria/Card_Back_Pandaria","enabled":true,"description":"","source_description":"","id":1,"name":"潘达利亚","source":"season","note_desc":"Pandaria"},{"prefab_name":"Assets/Game/CardBacks/S002_BlackTemple/Card_Back_BlackTemple","enabled":true,"description":"","source_description":"","id":2,"name":"黑暗神庙","source":"season","note_desc":"Black Temple"},{"prefab_name":"Assets/Game/CardBacks/S003_Charm/Card_Back_Charm","enabled":true,"description":"","source_description":"","id":3,"name":"炫丽彩虹","source":"season","note_desc":"Rainbow!"},{"prefab_name":"Assets/Game/CardBacks/Launch/Card_Back_Launch","enabled":true,"description":"","source_description":"","id":4,"name":"炉边好友","source":"achieve","note_desc":"Fireside"},{"prefab_name":"Assets/Game/CardBacks/Legend/Card_Back_Legend","enabled":true,"description":"","source_description":"","id":5,"name":"我是传说","source":"achieve","note_desc":"Legend"},{"prefab_name":"Assets/Game/CardBacks/Naxxramas/Card_Back_Naxxramas","enabled":true,"description":"","source_description":"","id":6,"name":"纳克萨玛斯","source":"season","note_desc":"Naxxramas"},{"prefab_name":"Assets/Game/CardBacks/Naxxramas2/Card_Back_Naxxramas2","enabled":true,"description":"","source_description":"","id":7,"name":"英雄纳克萨玛斯","source":"fixed_reward","note_desc":"Heroic Naxxramas"},{"prefab_name":"Assets/Game/CardBacks/IceCrown/Card_Back_IceCrown","enabled":true,"description":"","source_description":"","id":8,"name":"冰冠冰川","source":"season","note_desc":"Icecrown"},{"prefab_name":"Assets/Game/CardBacks/Pirate/Card_Back_Pirate","enabled":false,"description":"","source_description":"","id":9,"name":"惊涛骇浪","source":"season","note_desc":"Pirates!"},{"prefab_name":"Assets/Game/CardBacks/Hallows_End/Card_Back_Hallows_End","enabled":false,"description":"","source_description":"","id":10,"name":"万圣节","source":"season","note_desc":"Hallow's End"},{"prefab_name":"Assets/Game/CardBacks/Goblin/Card_Back_Goblin","enabled":false,"description":"","source_description":"","id":11,"name":"地精科技","source":"season","note_desc":"Goblins"},{"prefab_name":"Assets/Game/CardBacks/Blizzard2014/Card_Back_Blizzard2014","enabled":false,"description":"","source_description":"","id":12,"name":"暴雪2014","source":"achieve","note_desc":"Blizzard 2014"},{"prefab_name":"Assets/Game/CardBacks/TeSPA/Card_Back_TeSPA","enabled":false,"description":"","source_description":"","id":13,"name":"达拉然火焰","source":"achieve","note_desc":"Dalaran Flame"},{"prefab_name":"Assets/Game/CardBacks/Warlords_of_Draenor/Card_Back_Warlords_of_Draenor","enabled":false,"description":"","source_description":"","id":14,"name":"战争之王","source":"achieve","note_desc":"Warlords"},{"prefab_name":"Assets/Game/CardBacks/Gnome/Card_Back_Gnome","enabled":true,"description":"","source_description":"","id":15,"name":"诺莫瑞根","source":"season","note_desc":"Gnomes"},{"prefab_name":"Assets/Game/CardBacks/Maraad/Card_Back_Maraad","enabled":true,"description":"","source_description":"","id":16,"name":"圣光悍将","source":"season","note_desc":"Maraad"},{"prefab_name":"Assets/Game/CardBacks/Lunar/Card_Back_Lunar","enabled":true,"description":"","source_description":"","id":17,"name":"新年吉祥","source":"season","note_desc":"Lunar New Year"},{"prefab_name":"Assets/Game/CardBacks/MoltenCore/Card_Back_MoltonCore","enabled":true,"description":"","source_description":"","id":18,"name":"熔火之心","source":"achieve","note_desc":"Molten Core"},{"prefab_name":"Assets/Game/CardBacks/Ragnaros/Card_Back_Ragnaros","enabled":true,"description":"","source_description":"","id":19,"name":"炎魔之王","source":"season","note_desc":"Ragnaros"},{"prefab_name":"Assets/Game/CardBacks/GoldenCelebration/Card_Back_GoldenCelebration","enabled":true,"description":"","source_description":"","id":20,"name":"黄金挑战","source":"achieve","note_desc":"Golden Celebration"},{"prefab_name":"Assets/Game/CardBacks/Nefarian/Card_Back_Nefarian","enabled":true,"description":"","source_description":"","id":21,"name":"奈法利安","source":"fixed_reward","note_desc":"Heroic BRM"},{"prefab_name":"Assets/Game/CardBacks/Cupcake/Card_Back_Cupcake","enabled":true,"description":"","source_description":"","id":22,"name":"甜蜜胜利","source":"season","note_desc":"Cupcake"},{"prefab_name":"Assets/Game/CardBacks/Ninja/Card_Back_Ninja","enabled":true,"description":"","source_description":"","id":23,"name":"忍者无敌","source":"season","note_desc":"Ninjas!"},{"prefab_name":"Assets/Game/CardBacks/HotS/Card_Back_HotS","enabled":true,"description":"","source_description":"","id":24,"name":"风暴英雄","source":"achieve","note_desc":"Heroes of the Storm"}]